[
  {
    "block_index": 1,
    "timestamp": "1635884545.",
    "nonce": 1276119849,
    "transactions": [
      { "sender": "Knicks", "receiver": "Lakers", "amount": 60000000.0 },
      {
        "sender": "Timberwolves",
        "receiver": "Knicks",
        "amount": 24000000.0
      },
      { "sender": "Wizards", "receiver": "Lakers", "amount": 34000000.0 },
      { "sender": "Wizards", "receiver": "Lakers", "amount": 34000000.0 },
      { "sender": "Knicks", "receiver": "Lakers", "amount": 60000000.0 }
    ],
    "prev_hash":
      "883e47459066d508517b2ad662e44f6547aa48ee7c87463ea17b826246701fd0",
    "hash":
      "90d85e9e90b4e7be5808ca8d83c91ad9e0ccb0e8dca0cbed85dde7d633acc470"
  },
  {
    "block_index": 0,
    "timestamp": "1631761355.",
    "nonce": 0,
    "transactions": [],
    "prev_hash":
      "0000000000000000000000000000000000000000000000000000000000000000",
    "hash":
      "883e47459066d508517b2ad662e44f6547aa48ee7c87463ea17b826246701fd0"
  }
]